ayz_auth/__init__.py
ayz_auth/decorators.py
ayz_auth/middleware.py
ayz_auth/auth/__init__.py
ayz_auth/auth/stytch_verifier.py
ayz_auth/auth/token_extractor.py
ayz_auth/cache/__init__.py
ayz_auth/cache/redis_client.py
ayz_auth/db/__init__.py
ayz_auth/db/entitlements_loader.py
ayz_auth/db/mongo_client.py
ayz_auth/models/__init__.py
ayz_auth/models/context.py
ayz_auth/utils/__init__.py
ayz_auth/utils/config.py
ayz_auth/utils/exceptions.py
ayz_auth/utils/logger.py
ayz_auth-2.2.1.dist-info/METADATA
ayz_auth-2.2.1.dist-info/WHEEL
ayz_auth-2.2.1.dist-info/RECORD
