Metadata-Version: 2.4
Name: ayz-auth
Version: 2.2.1
Summary: FastAPI middleware for Stytch B2B authentication with Redis caching, MongoDB entitlements, and team context
Project-URL: Homepage, https://github.com/ayzenberg/ayz-auth
Project-URL: Repository, https://github.com/ayzenberg/ayz-auth
Project-URL: Issues, https://github.com/ayzenberg/ayz-auth/issues
Author-email: Ayzenberg <dev@ayzenberg.com>
License: MIT
Keywords: authentication,authorization,b2b,entitlements,fastapi,middleware,stytch
Classifier: Development Status :: 4 - Beta
Classifier: Framework :: FastAPI
Classifier: Intended Audience :: Developers
Classifier: License :: OSI Approved :: MIT License
Classifier: Programming Language :: Python :: 3
Classifier: Programming Language :: Python :: 3.8
Classifier: Programming Language :: Python :: 3.9
Classifier: Programming Language :: Python :: 3.10
Classifier: Programming Language :: Python :: 3.11
Classifier: Programming Language :: Python :: 3.12
Classifier: Topic :: Internet :: WWW/HTTP :: HTTP Servers
Classifier: Topic :: Security
Requires-Python: >=3.8
Requires-Dist: fastapi>=0.100.0
Requires-Dist: httpx>=0.24.0
Requires-Dist: pydantic-settings>=2.0.0
Requires-Dist: pydantic>=2.0.0
Requires-Dist: python-multipart>=0.0.6
Requires-Dist: redis>=4.5.0
Requires-Dist: stytch>=5.0.0
Requires-Dist: typing-extensions>=4.0.0
Provides-Extra: dev
Requires-Dist: black>=23.0.0; extra == 'dev'
Requires-Dist: fakeredis>=2.10.0; extra == 'dev'
Requires-Dist: httpx>=0.24.0; extra == 'dev'
Requires-Dist: isort>=5.12.0; extra == 'dev'
Requires-Dist: mongomock-motor>=0.0.21; extra == 'dev'
Requires-Dist: mypy>=1.0.0; extra == 'dev'
Requires-Dist: pytest-asyncio>=0.21.0; extra == 'dev'
Requires-Dist: pytest-mock>=3.10.0; extra == 'dev'
Requires-Dist: pytest>=7.0.0; extra == 'dev'
Requires-Dist: ruff>=0.1.0; extra == 'dev'
Provides-Extra: mongodb
Requires-Dist: motor>=3.0.0; extra == 'mongodb'
Requires-Dist: pymongo>=4.0.0; extra == 'mongodb'
